pynfce/__init__.py
pynfce/nfce/__init__.py
pynfce/nfce/nfce.py
pynfce/states/__init__.py
pynfce/states/ba.py
pynfce/states/crawling.py
pynfce/states/states.py
pynfce-0.3.1.dist-info/WHEEL
pynfce-0.3.1.dist-info/METADATA
pynfce-0.3.1.dist-info/RECORD
