Metadata-Version: 2.1
Name: pynfce
Version: 0.3.1
Summary: 
Home-page: UNKNOWN
License: UNKNOWN
Author: Matheus Cardoso
Author-email: matheus.mcas@gmail.com
Requires-Python: >=3.7,<4.0
Classifier: Programming Language :: Python :: 3
Classifier: Programming Language :: Python :: 3.7
Requires-Dist: requests-html (>=0.10.0,<0.11.0)
